frojd_intranet
