Metadata-Version: 1.0
Name: frojd-intranet
Version: 1.0.3
Summary: CLI tool for the frojd intranet
Home-page: http://frojd.se
Author: Fröjd
Author-email: martin.sandstrom@frojd.se
License: MIT
Platform: UNKNOWN
